{
    "ID": "etcd",
    "Properties": {
        "Allocation": {
            "LogicalIDs": [
                "192.168.65.200",
                "192.168.65.201",
                "192.168.65.202"
            ]
        },
        "Instance": {
            "Plugin": "instance-hyperkit",
            "Properties": {
                "Moby": "etcd",
                "Disk" : 0,
                "CPUs" : 1,
                "Memory" : 1024
            }
        },
        "Flavor": {
            "Plugin": "flavor-vanilla",
            "Properties": {
                "Init": [
                ],
                "Tags": {
                    "tier": "etcd-cluster",
                    "project": "infrakit"
                }
            }
        }
    }
}
